novemberff/__init__.py
novemberff/_core/__init__.py
novemberff/_core/bond_graph.py
novemberff/_core/energy_calculator.py
novemberff/_forcefield/__init__.py
novemberff/_forcefield/angles.py
novemberff/_forcefield/bonds.py
novemberff/_forcefield/dihedrals.py
novemberff/_forcefield/forcefield.py
novemberff/_forcefield/interaction.py
novemberff/_forcefield/nonbonded.py
novemberff/_forcefield/particles.py
novemberff/_misc/__init__.py
novemberff/_misc/utils.py
novemberff/_parsers/__init__.py
novemberff/_parsers/_tables.py
novemberff/_parsers/ffparser.py
novemberff/_parsers/ffparser_xml.py
novemberff/_parsers/pdb_postprocess.py
novemberff-0.3.0.dist-info/licenses/LICENSE.md
novemberff-0.3.0.dist-info/METADATA
novemberff-0.3.0.dist-info/WHEEL
novemberff-0.3.0.dist-info/top_level.txt
novemberff-0.3.0.dist-info/RECORD
