Metadata-Version: 2.4
Name: novemberff
Version: 0.3.0
Summary: Custom implementation of the AMBER forcefield, focused on simplicity and verbose outputs.
Home-page: https://github.com/diegobarmor/novemberff
Author: DiegoBarMor
Author-email: diegobarmor42@gmail.com
License: MIT
Keywords: Amber Forcefield MolecularDynamics MD Simulation
Classifier: Programming Language :: Python :: 3
Classifier: License :: OSI Approved :: MIT License
Classifier: Operating System :: OS Independent
Requires-Python: >=3.10
License-File: LICENSE.md
Dynamic: author
Dynamic: author-email
Dynamic: classifier
Dynamic: description
Dynamic: description-content-type
Dynamic: home-page
Dynamic: keywords
Dynamic: license
Dynamic: license-file
Dynamic: requires-python
Dynamic: summary
